openbb_cboe/__init__.py
openbb_cboe/models/__init__.py
openbb_cboe/models/available_indices.py
openbb_cboe/models/equity_historical.py
openbb_cboe/models/equity_quote.py
openbb_cboe/models/equity_search.py
openbb_cboe/models/futures_curve.py
openbb_cboe/models/index_constituents.py
openbb_cboe/models/index_historical.py
openbb_cboe/models/index_search.py
openbb_cboe/models/index_snapshots.py
openbb_cboe/models/options_chains.py
openbb_cboe/py.typed
openbb_cboe/utils/__init__.py
openbb_cboe/utils/helpers.py
openbb_cboe/utils/vix.py
openbb_cboe-1.5.1.dist-info/METADATA
openbb_cboe-1.5.1.dist-info/WHEEL
openbb_cboe-1.5.1.dist-info/entry_points.txt
openbb_cboe-1.5.1.dist-info/RECORD
